sieveai/__init__.py
sieveai/cli.py
sieveai/exe/AnnapuRNA.py
sieveai/exe/ExecutableBase.py
sieveai/exe/Vina.py
sieveai/exe/VinaBase.py
sieveai/exe/__init__.py
sieveai/lib/ChimeraX.py
sieveai/lib/LibManager.py
sieveai/lib/MolConverter.py
sieveai/lib/OpenBabel.py
sieveai/lib/__init__.py
sieveai/process/Docking.py
sieveai/process/ProcessBase.py
sieveai/process/Rescoring.py
sieveai/process/__init__.py
SieveAI-0.7.1.dist-info/LICENSE
SieveAI-0.7.1.dist-info/METADATA
SieveAI-0.7.1.dist-info/WHEEL
SieveAI-0.7.1.dist-info/entry_points.txt
SieveAI-0.7.1.dist-info/top_level.txt
SieveAI-0.7.1.dist-info/RECORD
