Metadata-Version: 2.1
Name: SieveAI
Version: 0.7.1
Summary: SieveAI: An Automated Drug Discovery Pipeline
Author-email: Vishal Kumar Sahu <mail@vishalkumarsahu.in>
Project-URL: Homepage, https://github.com/TheBiomics/SieveAI
Project-URL: Issues, https://github.com/TheBiomics/SieveAI/issues
Classifier: Operating System :: OS Independent
Classifier: Intended Audience :: Science/Research
Classifier: Programming Language :: Python :: 3.8
Classifier: Programming Language :: Python :: 3.9
Classifier: Programming Language :: Python :: 3.10
Requires-Python: >=3.8
License-File: LICENSE
Requires-Dist: UtilityLib
Requires-Dist: biopython
Requires-Dist: imageio
Requires-Dist: lxml
Requires-Dist: numpy
Requires-Dist: pandas
Requires-Dist: pdb-tools
Requires-Dist: Pillow
Requires-Dist: psutil
Requires-Dist: PyAutoGUI
Requires-Dist: python3-xlib
Requires-Dist: requests
Requires-Dist: seaborn
Requires-Dist: SQLAlchemy
Requires-Dist: tqdm
